{
  "ComponentIndexes": {
    "AdmincompMenu": 22,
    "comMenu_H": 23,
    "Header": 24,
    "StudentcompMenu": 25,
    "TeachercompMenu": 26
  },
  "ControlUniqueIds": {
    "Admin Dashboard": 93,
    "Admin Knowledge": 109,
    "Admin Messaging": 117,
    "AdmincompMenu": 23,
    "AdmincompMenu_1": 108,
    "AdmincompMenu_2": 124,
    "AdmincompMenu_3": 116,
    "App": 1,
    "Button1": 174,
    "Button2": 146,
    "Button2_1": 147,
    "Button2_2": 148,
    "Button2_3": 149,
    "Button2_4": 150,
    "Button2_5": 151,
    "Button3": 172,
    "Button4": 173,
    "Button5": 85,
    "Button7": 10,
    "ButtonCallHealthAssured": 169,
    "ButtonCallOccHealth": 167,
    "Canvas1_1": 41,
    "Canvas1_2": 82,
    "Canvas1_3": 191,
    "Canvas1_4": 100,
    "Canvas1_5": 228,
    "Canvas3_1": 212,
    "Canvas3_2": 121,
    "Canvas3_3": 73,
    "Canvas4_1": 204,
    "Canvas4_2": 65,
    "Canvas4_3": 113,
    "CheckInButton_1": 38,
    "CheckInButton_2": 188,
    "CheckInButton_3": 97,
    "CheckInButton_4": 225,
    "comMenu_H": 29,
    "Container1": 43,
    "Container1_1": 230,
    "Container2": 48,
    "Container2_1": 52,
    "Container2_2": 56,
    "Container2_3": 235,
    "Container2_4": 239,
    "Container2_5": 243,
    "Container3": 7,
    "Container3_1": 4,
    "Daily Check In - Face": 125,
    "Daily Check In - Weather": 135,
    "Daily Check In - Word": 141,
    "DashboardLogo_1": 36,
    "DashboardLogo_2": 79,
    "DashboardLogo_3": 186,
    "DashboardLogo_4": 95,
    "DashboardLogo_5": 223,
    "DataCard1": 198,
    "DataCard1_1": 195,
    "DataCard1_2": 104,
    "DataCard1_3": 107,
    "DataCard10": 55,
    "DataCard10_1": 242,
    "DataCard14": 83,
    "DataCard2": 59,
    "DataCard2_1": 246,
    "DataCard3": 42,
    "DataCard3_1": 229,
    "DataCard4_1": 192,
    "DataCard4_2": 101,
    "DataCard6": 47,
    "DataCard6_1": 234,
    "DataCard7": 51,
    "DataCard7_1": 238,
    "DataCard8_1": 213,
    "DataCard8_2": 122,
    "DataCard8_3": 74,
    "DataCard9_1": 205,
    "DataCard9_2": 66,
    "DataCard9_3": 114,
    "Dropdown1": 84,
    "DropdownOrganisation": 159,
    "DropdownTopic": 157,
    "FurtherInformation": 153,
    "Gallery1": 30,
    "Gallery4": 12,
    "Gallery4_1": 24,
    "Gallery4_2": 18,
    "galleryTemplate2": 31,
    "galleryTemplate3": 13,
    "galleryTemplate3_1": 25,
    "galleryTemplate3_2": 20,
    "Header": 3,
    "Header_10": 203,
    "Header_11": 96,
    "Header_12": 120,
    "Header_13": 64,
    "Header_14": 112,
    "Header_15": 72,
    "Header_3": 37,
    "Header_4": 224,
    "Header_6": 80,
    "Header_7": 187,
    "Header_8": 181,
    "Header_9": 211,
    "Icon1": 152,
    "Icon1_1": 139,
    "Icon2": 132,
    "Icon2_1": 131,
    "Icon2_2": 133,
    "Icon2_3": 130,
    "Icon2_4": 134,
    "Icon6": 32,
    "Icon8": 15,
    "Icon8_1": 14,
    "Icon8_2": 26,
    "Icon8_3": 27,
    "Icon8_4": 19,
    "Icon8_5": 21,
    "IconBackFurtherInformation": 168,
    "IconCancel1_1": 142,
    "IconCancel1_2": 136,
    "IconCancel1_3": 126,
    "iconCheck1": 218,
    "iconCircle1": 217,
    "IconHome_1": 220,
    "IconMail": 164,
    "IconNextWelcome_1": 91,
    "IconPhone": 166,
    "Image1": 8,
    "Image10": 45,
    "Image10_1": 232,
    "Image4_1": 193,
    "Image4_2": 102,
    "Image6_1": 194,
    "Image6_2": 103,
    "Image7_1": 197,
    "Image7_2": 106,
    "Image8_1": 196,
    "Image8_2": 105,
    "ImageInternet": 162,
    "Label1": 129,
    "Label1_1": 145,
    "Label1_2": 140,
    "Label1_3": 128,
    "Label1_4": 144,
    "Label1_5": 138,
    "Label10_1": 206,
    "Label10_2": 67,
    "Label10_3": 115,
    "Label11": 49,
    "Label11_1": 53,
    "Label11_2": 57,
    "Label11_3": 236,
    "Label11_4": 240,
    "Label11_5": 244,
    "Label13": 182,
    "Label13_1": 214,
    "Label13_2": 123,
    "Label13_4": 75,
    "Label2": 33,
    "Label3": 9,
    "Label4": 6,
    "Label5": 81,
    "Label6": 16,
    "Label6_1": 28,
    "Label6_2": 22,
    "Label7": 44,
    "Label7_1": 231,
    "Label8": 176,
    "Label9": 46,
    "Label9_1": 233,
    "LabelCharityWebsiteURL": 161,
    "LabelEmailAddress": 163,
    "LabelEnter_1": 92,
    "LabelHeader_1": 87,
    "LabelMoreInformation": 154,
    "LabelOrganisationDropdown": 158,
    "LabelPhoneNumber": 165,
    "LabelText1": 178,
    "LabelText2": 179,
    "LabelText5": 155,
    "LabelText6": 160,
    "LabelTopicDropdown": 156,
    "LabelWelcome_1": 90,
    "LblAppName3_1": 210,
    "LblAppName3_2": 119,
    "LblAppName3_3": 71,
    "LblAppName4_1": 202,
    "LblAppName4_2": 63,
    "LblAppName4_3": 111,
    "LblSuccessMsg1": 219,
    "Log out": 170,
    "Login Role based": 171,
    "Logo": 89,
    "Logo_1": 88,
    "Logo_2": 5,
    "Logo_3": 127,
    "Logo_4": 143,
    "Logo_5": 137,
    "MonthlyButton_1": 40,
    "MonthlyButton_2": 190,
    "MonthlyButton_3": 99,
    "MonthlyButton_4": 227,
    "PowerBI2": 50,
    "PowerBI2_1": 54,
    "PowerBI2_2": 58,
    "PowerBI2_3": 237,
    "PowerBI2_4": 241,
    "PowerBI2_5": 245,
    "RectQuickActionBar3_1": 35,
    "RectQuickActionBar3_2": 78,
    "RectQuickActionBar3_3": 185,
    "RectQuickActionBar3_4": 94,
    "RectQuickActionBar3_5": 222,
    "RectQuickActionBar4_1": 209,
    "RectQuickActionBar4_2": 118,
    "RectQuickActionBar4_3": 70,
    "RectQuickActionBar5_1": 201,
    "RectQuickActionBar5_2": 62,
    "RectQuickActionBar5_3": 110,
    "Screen1": 175,
    "Start": 177,
    "Student Community": 180,
    "Student Dashboard": 184,
    "Student Knowledge": 200,
    "Student Messaging": 208,
    "StudentcompMenu": 11,
    "StudentcompMenu_1": 199,
    "StudentcompMenu_2": 183,
    "StudentcompMenu_3": 215,
    "StudentcompMenu_4": 207,
    "Success": 216,
    "Teacher Class Management": 221,
    "Teacher Dashboard": 34,
    "Teacher Knowledge": 61,
    "Teacher Messaging": 69,
    "Teacher QuestionSet": 77,
    "TeachercompMenu": 17,
    "TeachercompMenu_1": 60,
    "TeachercompMenu_2": 68,
    "TeachercompMenu_3": 247,
    "TeachercompMenu_4": 76,
    "WeeklyButton_1": 39,
    "WeeklyButton_2": 189,
    "WeeklyButton_3": 98,
    "WeeklyButton_4": 226,
    "Welcome": 86
  },
  "FunctionParamsInvariantScripts": {},
  "HeaderLastSavedDateTimeUTC": "04/06/2022 06:00:47",
  "IsLegacyComponentAllowGlobalScopeCase": false,
  "LocalDatabaseReferencesAsEmpty": false,
  "LocalResourceFileNames": {
    "background tree big": "0001.png",
    "background tree small": "0002.png",
    "default": "0003.jpg",
    "dialog": "0004.png",
    "global": "0005.png",
    "home page": "0006.png",
    "iPhone_Dialog": "0007.png",
    "Keep-it-simple": "0008.jpg",
    "mh logo": "0009.JPG",
    "Neutral": "0010.png",
    "No": "0011.png",
    "Picture1": "0012.png",
    "Picture1_1": "0013.png",
    "Picture2": "0014.png",
    "Picture2_1": "0021.png",
    "Picture2_2": "0022.png",
    "Picture21": "0015.png",
    "Picture21_1": "0016.png",
    "Picture22": "0017.png",
    "Picture22_1": "0018.png",
    "Picture23": "0019.png",
    "Picture23_1": "0020.png",
    "Picture3": "0023.png",
    "Picture3_1": "0024.png",
    "Picture6": "0025.png",
    "Picture6_1": "0026.png",
    "Questions": "0027.png",
    "right swish": "0028.png",
    "tree": "0029.JPG",
    "Yes": "0030.png"
  },
  "LocalResourceRootPaths": {
    "background tree big": "https://docserverpwaprodeau.blob.core.windows.net/f8c520a7-e838-462f-a5b5-98a99e3a4346-1/resource/Assets0Images00001.png?sv=2017-04-17&sr=b&sig=p7yzOD8hZBWXgFdvBdUMgqNZRZi582X7zW7eNwYiwB4%3D&spr=https&se=2022-04-07T06%3A13%3A42Z&sp=r",
    "background tree small": "https://docserverpwaprodeau.blob.core.windows.net/f8c520a7-e838-462f-a5b5-98a99e3a4346-1/resource/Assets0Images00002.png?sv=2017-04-17&sr=b&sig=VtTIicq1J3UG8TTlk0ffzmHDUUrwgDZU5b%2BCz8HWlgA%3D&spr=https&se=2022-04-07T06%3A13%3A42Z&sp=r",
    "default": "https://docserverpwaprodeau.blob.core.windows.net/f8c520a7-e838-462f-a5b5-98a99e3a4346-1/resource/Assets0Images00003.jpg?sv=2017-04-17&sr=b&sig=5XfFw2Z2GISNvo2KA4EAKyjyP2MMjZ0ugO508VCsNuQ%3D&spr=https&se=2022-04-07T06%3A13%3A42Z&sp=r",
    "dialog": "https://docserverpwaprodeau.blob.core.windows.net/f8c520a7-e838-462f-a5b5-98a99e3a4346-1/resource/Assets0Images00004.png?sv=2017-04-17&sr=b&sig=pDcR%2BrezxgCICnS5zDoLKgoDr3mOkPsr48v7rcXk9Ng%3D&spr=https&se=2022-04-07T06%3A13%3A42Z&sp=r",
    "global": "https://docserverpwaprodeau.blob.core.windows.net/f8c520a7-e838-462f-a5b5-98a99e3a4346-1/resource/Assets0Images00005.png?sv=2017-04-17&sr=b&sig=tg3FRiYpnZ4DarDzFx8VY3Ifd0PbRmuO5nw5XcwakC8%3D&spr=https&se=2022-04-07T06%3A13%3A42Z&sp=r",
    "home page": "https://docserverpwaprodeau.blob.core.windows.net/f8c520a7-e838-462f-a5b5-98a99e3a4346-1/resource/Assets0Images00006.png?sv=2017-04-17&sr=b&sig=YWhtK5wWgFPDVEXEgUvc4%2FJhFvf3MRB6i1%2FYEdWfjOo%3D&spr=https&se=2022-04-07T06%3A13%3A42Z&sp=r",
    "iPhone_Dialog": "https://docserverpwaprodeau.blob.core.windows.net/f8c520a7-e838-462f-a5b5-98a99e3a4346-1/resource/Assets0Images00007.png?sv=2017-04-17&sr=b&sig=LILx80qi93yGqfssUhSQHRiNEjww5OnneOaHkLwyhcU%3D&spr=https&se=2022-04-07T06%3A13%3A42Z&sp=r",
    "Keep-it-simple": "https://docserverpwaprodeau.blob.core.windows.net/f8c520a7-e838-462f-a5b5-98a99e3a4346-1/resource/Assets0Images00008.jpg?sv=2017-04-17&sr=b&sig=svDETa5hGWOwHTpjPM9Ad1MesKfhGvavdVLdUEfrOTg%3D&spr=https&se=2022-04-07T06%3A13%3A42Z&sp=r",
    "mh logo": "https://docserverpwaprodeau.blob.core.windows.net/f8c520a7-e838-462f-a5b5-98a99e3a4346-1/resource/Assets0Images00009.JPG?sv=2017-04-17&sr=b&sig=tDwRwNk6qt0VIQPvz5XG9r66lr20belDprbYHmJaDVc%3D&spr=https&se=2022-04-07T06%3A13%3A42Z&sp=r",
    "Neutral": "https://docserverpwaprodeau.blob.core.windows.net/f8c520a7-e838-462f-a5b5-98a99e3a4346-1/resource/Assets0Images00010.png?sv=2017-04-17&sr=b&sig=49qkGd%2FH%2BR6bLexD2aqsi8GU5EnpnYlNelNQal5ngxw%3D&spr=https&se=2022-04-07T06%3A13%3A42Z&sp=r",
    "No": "https://docserverpwaprodeau.blob.core.windows.net/f8c520a7-e838-462f-a5b5-98a99e3a4346-1/resource/Assets0Images00011.png?sv=2017-04-17&sr=b&sig=5iOXBRw8AjBcFsweXoMHURM0FCvDZd2QrHiTpYXIOio%3D&spr=https&se=2022-04-07T06%3A13%3A42Z&sp=r",
    "Picture1": "https://docserverpwaprodeau.blob.core.windows.net/f8c520a7-e838-462f-a5b5-98a99e3a4346-1/resource/Assets0Images00012.png?sv=2017-04-17&sr=b&sig=wREnkczGAMthp4IZW5MG2oEbcG1QYuslIm%2F0qEAm2eo%3D&spr=https&se=2022-04-07T06%3A13%3A42Z&sp=r",
    "Picture1_1": "https://docserverpwaprodeau.blob.core.windows.net/f8c520a7-e838-462f-a5b5-98a99e3a4346-1/resource/Assets0Images00013.png?sv=2017-04-17&sr=b&sig=SHKXzLwOIzSvX%2B%2FHmtwj1rEeaKfaZbb779GV%2FfhMNqE%3D&spr=https&se=2022-04-07T06%3A13%3A42Z&sp=r",
    "Picture2": "https://docserverpwaprodeau.blob.core.windows.net/f8c520a7-e838-462f-a5b5-98a99e3a4346-1/resource/Assets0Images00014.png?sv=2017-04-17&sr=b&sig=xzMNNuQNnG1mjqfGAzuNsfNh2G4qiGiiVYLFnMzxhJE%3D&spr=https&se=2022-04-07T06%3A13%3A42Z&sp=r",
    "Picture2_1": "https://docserverpwaprodeau.blob.core.windows.net/f8c520a7-e838-462f-a5b5-98a99e3a4346-1/resource/Assets0Images00021.png?sv=2017-04-17&sr=b&sig=FhuyXXTUf2vithzv9KJ3EeRvQTyqrCybhHsLchnry2U%3D&spr=https&se=2022-04-07T06%3A13%3A42Z&sp=r",
    "Picture2_2": "https://docserverpwaprodeau.blob.core.windows.net/f8c520a7-e838-462f-a5b5-98a99e3a4346-1/resource/Assets0Images00022.png?sv=2017-04-17&sr=b&sig=mIeQaQ5FR6hJzskxAc0Rmn%2B%2FCrFfMmTcjVtD91ycv58%3D&spr=https&se=2022-04-07T06%3A13%3A42Z&sp=r",
    "Picture21": "https://docserverpwaprodeau.blob.core.windows.net/f8c520a7-e838-462f-a5b5-98a99e3a4346-1/resource/Assets0Images00015.png?sv=2017-04-17&sr=b&sig=R6qmqL6p0dyXiLn5Ojt1VU4RwvRhjP2X3U9wFfNMahw%3D&spr=https&se=2022-04-07T06%3A13%3A42Z&sp=r",
    "Picture21_1": "https://docserverpwaprodeau.blob.core.windows.net/f8c520a7-e838-462f-a5b5-98a99e3a4346-1/resource/Assets0Images00016.png?sv=2017-04-17&sr=b&sig=vyLWx3t4DPHjkFQlR9j7hHwIr0Pf%2BAeq%2FFQsjeZzrts%3D&spr=https&se=2022-04-07T06%3A13%3A42Z&sp=r",
    "Picture22": "https://docserverpwaprodeau.blob.core.windows.net/f8c520a7-e838-462f-a5b5-98a99e3a4346-1/resource/Assets0Images00017.png?sv=2017-04-17&sr=b&sig=h8VPcG1reQnxltltki7m2AQ8DY6t4CCOAv87f1U058Y%3D&spr=https&se=2022-04-07T06%3A13%3A42Z&sp=r",
    "Picture22_1": "https://docserverpwaprodeau.blob.core.windows.net/f8c520a7-e838-462f-a5b5-98a99e3a4346-1/resource/Assets0Images00018.png?sv=2017-04-17&sr=b&sig=WlipMyUpWRQFQBPB77OoI1Onc%2FnZhJztBSrhiQVxpyw%3D&spr=https&se=2022-04-07T06%3A13%3A42Z&sp=r",
    "Picture23": "https://docserverpwaprodeau.blob.core.windows.net/f8c520a7-e838-462f-a5b5-98a99e3a4346-1/resource/Assets0Images00019.png?sv=2017-04-17&sr=b&sig=6CmUqmtZdg%2F8F30bDooLIVPBNIeX1PkxOiJ1tkKedB4%3D&spr=https&se=2022-04-07T06%3A13%3A42Z&sp=r",
    "Picture23_1": "https://docserverpwaprodeau.blob.core.windows.net/f8c520a7-e838-462f-a5b5-98a99e3a4346-1/resource/Assets0Images00020.png?sv=2017-04-17&sr=b&sig=rVh1MfNXg1V%2FGHvMphNaA%2BWaOU9RPPHHXSbVvlT9hZc%3D&spr=https&se=2022-04-07T06%3A13%3A42Z&sp=r",
    "Picture3": "https://docserverpwaprodeau.blob.core.windows.net/f8c520a7-e838-462f-a5b5-98a99e3a4346-1/resource/Assets0Images00023.png?sv=2017-04-17&sr=b&sig=U%2FQbL7Bc3yKxUe0okyNAWY2tQmnFuZTOng%2Fw3CWyt6E%3D&spr=https&se=2022-04-07T06%3A13%3A42Z&sp=r",
    "Picture3_1": "https://docserverpwaprodeau.blob.core.windows.net/f8c520a7-e838-462f-a5b5-98a99e3a4346-1/resource/Assets0Images00024.png?sv=2017-04-17&sr=b&sig=kulWubMPYyrVvSB2HMlCUOjm1i%2FtSX8%2FbRx6B42N4jo%3D&spr=https&se=2022-04-07T06%3A13%3A42Z&sp=r",
    "Picture6": "https://docserverpwaprodeau.blob.core.windows.net/f8c520a7-e838-462f-a5b5-98a99e3a4346-1/resource/Assets0Images00025.png?sv=2017-04-17&sr=b&sig=4ou4CGGv0sTLNPuExpO2hHZw3q9Zyh9NWRUCkSBuqsE%3D&spr=https&se=2022-04-07T06%3A13%3A42Z&sp=r",
    "Picture6_1": "https://docserverpwaprodeau.blob.core.windows.net/f8c520a7-e838-462f-a5b5-98a99e3a4346-1/resource/Assets0Images00026.png?sv=2017-04-17&sr=b&sig=417Ccssc%2BIstwRIzRKT6IbVyag92OsgO4ErAeqcmk2g%3D&spr=https&se=2022-04-07T06%3A13%3A42Z&sp=r",
    "Questions": "https://docserverpwaprodeau.blob.core.windows.net/f8c520a7-e838-462f-a5b5-98a99e3a4346-1/resource/Assets0Images00027.png?sv=2017-04-17&sr=b&sig=tYAXpX3CVgCTnYftHjfS75AjzneMu%2FhQZmnB7ZmV1ow%3D&spr=https&se=2022-04-07T06%3A13%3A42Z&sp=r",
    "right swish": "https://docserverpwaprodeau.blob.core.windows.net/f8c520a7-e838-462f-a5b5-98a99e3a4346-1/resource/Assets0Images00028.png?sv=2017-04-17&sr=b&sig=328iktn9OcOYGqkPGvWQF1zF2e9sYEygypSYpjIeqz8%3D&spr=https&se=2022-04-07T06%3A13%3A42Z&sp=r",
    "tree": "https://docserverpwaprodeau.blob.core.windows.net/f8c520a7-e838-462f-a5b5-98a99e3a4346-1/resource/Assets0Images00029.JPG?sv=2017-04-17&sr=b&sig=4uXD87DxzBYqaNb17k8G%2BVPsWLdgz9T0J36dvAbSWrg%3D&spr=https&se=2022-04-07T06%3A13%3A42Z&sp=r",
    "Yes": "https://docserverpwaprodeau.blob.core.windows.net/f8c520a7-e838-462f-a5b5-98a99e3a4346-1/resource/Assets0Images00030.png?sv=2017-04-17&sr=b&sig=1j3Z5zd4st8o44m13rSlhHJOpGepVHeW%2BNSqdELWalI%3D&spr=https&se=2022-04-07T06%3A13%3A42Z&sp=r"
  },
  "OldLogoFileName": "logo.jpg",
  "OrderComponentMetadata": {
    "2924002d10ef4e43b50b5d656ee3735f": 4,
    "3e5effa7fd394095b1a41fcfb3450efc": 1,
    "49202fb1a47e43bab329824e5acc0c3a": 2,
    "55e5d1e89528422287eaec6afd3fecd3": 3,
    "aca5d404483a445aab9ac635139797ea": 0
  },
  "OrderComponentTemplate": {
    "2924002d10ef4e43b50b5d656ee3735f": 4,
    "3e5effa7fd394095b1a41fcfb3450efc": 1,
    "49202fb1a47e43bab329824e5acc0c3a": 2,
    "55e5d1e89528422287eaec6afd3fecd3": 3,
    "aca5d404483a445aab9ac635139797ea": 0
  },
  "OrderDataSource": {
    "Areyouokmain": 0,
    "check_in_face": 2,
    "check_in_word": 3,
    "check_in_word_1": 4,
    "checkin_face": 1,
    "ClassDetail": 22,
    "Collection1": 29,
    "CustomGallerySample": 23,
    "DropDownSample": 24,
    "face_checkin_click": 5,
    "face_checkin_click_1": 6,
    "face_checkin_click_10": 7,
    "face_checkin_click_11": 8,
    "face_checkin_click_12": 9,
    "face_checkin_click_13": 10,
    "face_checkin_click_14": 11,
    "face_checkin_click_15": 12,
    "face_checkin_click_2": 13,
    "face_checkin_click_3": 14,
    "face_checkin_click_4": 15,
    "face_checkin_click_5": 16,
    "face_checkin_click_6": 17,
    "face_checkin_click_7": 18,
    "face_checkin_click_8": 19,
    "face_checkin_click_9": 20,
    "Login": 25,
    "NavAdminView": 30,
    "NavStudentView": 31,
    "NavTeacherView": 32,
    "Office365Users": 21,
    "Resources by Topic Area": 26,
    "Response": 27,
    "Table1": 28
  },
  "OrderGroupControls": {},
  "OrderTemplate": {},
  "OrderXMLTemplate": {
    "button": 4,
    "circle": 10,
    "dropdown": 9,
    "fluidGrid": 5,
    "gallery": 7,
    "groupContainer": 2,
    "icon": 8,
    "image": 1,
    "label": 3,
    "powerbi": 6,
    "rectangle": 0
  },
  "PublishOrderIndices": {
    "Admin Dashboard": 32,
    "Admin Knowledge": 48,
    "Admin Messaging": 56,
    "AdmincompMenu": 1,
    "AdmincompMenu_1": 40,
    "AdmincompMenu_2": 61,
    "AdmincompMenu_3": 53,
    "App": 0,
    "Button1": 114,
    "Button2": 86,
    "Button2_1": 87,
    "Button2_2": 88,
    "Button2_3": 89,
    "Button2_4": 90,
    "Button2_5": 91,
    "Button3": 112,
    "Button4": 113,
    "Button5": 237,
    "Button7": 19,
    "ButtonCallHealthAssured": 109,
    "ButtonCallOccHealth": 107,
    "Canvas1_1": 195,
    "Canvas1_2": 236,
    "Canvas1_3": 131,
    "Canvas1_4": 39,
    "Canvas1_5": 168,
    "Canvas3_1": 152,
    "Canvas3_2": 60,
    "Canvas3_3": 227,
    "Canvas4_1": 144,
    "Canvas4_2": 219,
    "Canvas4_3": 52,
    "CheckInButton_1": 192,
    "CheckInButton_2": 128,
    "CheckInButton_3": 36,
    "CheckInButton_4": 165,
    "comMenu_H": 7,
    "Container1": 202,
    "Container1_1": 175,
    "Container2": 206,
    "Container2_1": 209,
    "Container2_2": 212,
    "Container2_3": 179,
    "Container2_4": 182,
    "Container2_5": 185,
    "Container3": 14,
    "Container3_1": 13,
    "Daily Check In - Face": 65,
    "Daily Check In - Weather": 75,
    "Daily Check In - Word": 81,
    "DashboardLogo_1": 190,
    "DashboardLogo_2": 233,
    "DashboardLogo_3": 126,
    "DashboardLogo_4": 34,
    "DashboardLogo_5": 163,
    "DataCard1": 135,
    "DataCard1_1": 134,
    "DataCard1_2": 42,
    "DataCard1_3": 43,
    "DataCard10": 200,
    "DataCard10_1": 173,
    "DataCard14": 238,
    "DataCard2": 201,
    "DataCard2_1": 174,
    "DataCard3": 197,
    "DataCard3_1": 170,
    "DataCard4_1": 133,
    "DataCard4_2": 41,
    "DataCard6": 198,
    "DataCard6_1": 171,
    "DataCard7": 199,
    "DataCard7_1": 172,
    "DataCard8_1": 154,
    "DataCard8_2": 62,
    "DataCard8_3": 229,
    "DataCard9_1": 146,
    "DataCard9_2": 221,
    "DataCard9_3": 54,
    "Dropdown1": 239,
    "DropdownOrganisation": 99,
    "DropdownTopic": 97,
    "FurtherInformation": 93,
    "Gallery1": 8,
    "Gallery4": 21,
    "Gallery4_1": 2,
    "Gallery4_2": 27,
    "galleryTemplate2": 9,
    "galleryTemplate3": 22,
    "galleryTemplate3_1": 3,
    "galleryTemplate3_2": 29,
    "Header": 12,
    "Header_10": 143,
    "Header_11": 35,
    "Header_12": 59,
    "Header_13": 218,
    "Header_14": 51,
    "Header_15": 226,
    "Header_3": 191,
    "Header_4": 164,
    "Header_6": 234,
    "Header_7": 127,
    "Header_8": 121,
    "Header_9": 151,
    "Icon1": 92,
    "Icon1_1": 79,
    "Icon2": 72,
    "Icon2_1": 71,
    "Icon2_2": 73,
    "Icon2_3": 70,
    "Icon2_4": 74,
    "Icon6": 10,
    "Icon8": 24,
    "Icon8_1": 23,
    "Icon8_2": 4,
    "Icon8_3": 5,
    "Icon8_4": 28,
    "Icon8_5": 30,
    "IconBackFurtherInformation": 108,
    "IconCancel1_1": 82,
    "IconCancel1_2": 76,
    "IconCancel1_3": 66,
    "iconCheck1": 158,
    "iconCircle1": 157,
    "IconHome_1": 160,
    "IconMail": 104,
    "IconNextWelcome_1": 245,
    "IconPhone": 106,
    "Image1": 17,
    "Image10": 204,
    "Image10_1": 177,
    "Image4_1": 136,
    "Image4_2": 44,
    "Image6_1": 137,
    "Image6_2": 45,
    "Image7_1": 139,
    "Image7_2": 47,
    "Image8_1": 138,
    "Image8_2": 46,
    "ImageInternet": 102,
    "Label1": 69,
    "Label1_1": 85,
    "Label1_2": 80,
    "Label1_3": 68,
    "Label1_4": 84,
    "Label1_5": 78,
    "Label10_1": 147,
    "Label10_2": 222,
    "Label10_3": 55,
    "Label11": 207,
    "Label11_1": 210,
    "Label11_2": 213,
    "Label11_3": 180,
    "Label11_4": 183,
    "Label11_5": 186,
    "Label13": 122,
    "Label13_1": 155,
    "Label13_2": 63,
    "Label13_4": 230,
    "Label2": 11,
    "Label3": 18,
    "Label4": 16,
    "Label5": 235,
    "Label6": 25,
    "Label6_1": 6,
    "Label6_2": 31,
    "Label7": 203,
    "Label7_1": 176,
    "Label8": 116,
    "Label9": 205,
    "Label9_1": 178,
    "LabelCharityWebsiteURL": 101,
    "LabelEmailAddress": 103,
    "LabelEnter_1": 246,
    "LabelHeader_1": 241,
    "LabelMoreInformation": 94,
    "LabelOrganisationDropdown": 98,
    "LabelPhoneNumber": 105,
    "LabelText1": 118,
    "LabelText2": 119,
    "LabelText5": 95,
    "LabelText6": 100,
    "LabelTopicDropdown": 96,
    "LabelWelcome_1": 244,
    "LblAppName3_1": 150,
    "LblAppName3_2": 58,
    "LblAppName3_3": 225,
    "LblAppName4_1": 142,
    "LblAppName4_2": 217,
    "LblAppName4_3": 50,
    "LblSuccessMsg1": 159,
    "Log out": 110,
    "Login Role based": 111,
    "Logo": 243,
    "Logo_1": 242,
    "Logo_2": 15,
    "Logo_3": 67,
    "Logo_4": 83,
    "Logo_5": 77,
    "MonthlyButton_1": 194,
    "MonthlyButton_2": 130,
    "MonthlyButton_3": 38,
    "MonthlyButton_4": 167,
    "PowerBI2": 208,
    "PowerBI2_1": 211,
    "PowerBI2_2": 214,
    "PowerBI2_3": 181,
    "PowerBI2_4": 184,
    "PowerBI2_5": 187,
    "RectQuickActionBar3_1": 189,
    "RectQuickActionBar3_2": 232,
    "RectQuickActionBar3_3": 125,
    "RectQuickActionBar3_4": 33,
    "RectQuickActionBar3_5": 162,
    "RectQuickActionBar4_1": 149,
    "RectQuickActionBar4_2": 57,
    "RectQuickActionBar4_3": 224,
    "RectQuickActionBar5_1": 141,
    "RectQuickActionBar5_2": 216,
    "RectQuickActionBar5_3": 49,
    "Screen1": 115,
    "Start": 117,
    "Student Community": 120,
    "Student Dashboard": 124,
    "Student Knowledge": 140,
    "Student Messaging": 148,
    "StudentcompMenu": 20,
    "StudentcompMenu_1": 132,
    "StudentcompMenu_2": 123,
    "StudentcompMenu_3": 153,
    "StudentcompMenu_4": 145,
    "Success": 156,
    "Teacher Class Management": 161,
    "Teacher Dashboard": 188,
    "Teacher Knowledge": 215,
    "Teacher Messaging": 223,
    "Teacher QuestionSet": 231,
    "TeachercompMenu": 26,
    "TeachercompMenu_1": 196,
    "TeachercompMenu_2": 220,
    "TeachercompMenu_3": 169,
    "TeachercompMenu_4": 228,
    "WeeklyButton_1": 193,
    "WeeklyButton_2": 129,
    "WeeklyButton_3": 37,
    "WeeklyButton_4": 166,
    "Welcome": 240
  },
  "ResourcesJsonIndices": {
    "Image-background tree big": 1,
    "Image-background tree small": 2,
    "Image-default": 3,
    "Image-dialog": 4,
    "Image-global": 5,
    "Image-home page": 6,
    "Image-iPhone_Dialog": 7,
    "Image-Keep-it-simple": 8,
    "Image-mh logo": 9,
    "Image-Neutral": 10,
    "Image-No": 11,
    "Image-Picture1": 12,
    "Image-Picture1_1": 13,
    "Image-Picture2": 14,
    "Image-Picture2_1": 21,
    "Image-Picture2_2": 22,
    "Image-Picture21": 15,
    "Image-Picture21_1": 16,
    "Image-Picture22": 17,
    "Image-Picture22_1": 18,
    "Image-Picture23": 19,
    "Image-Picture23_1": 20,
    "Image-Picture3": 23,
    "Image-Picture3_1": 24,
    "Image-Picture6": 25,
    "Image-Picture6_1": 26,
    "Image-Questions": 27,
    "Image-right swish": 28,
    "Image-SampleImage": 0,
    "Image-tree": 29,
    "Image-Yes": 30
  },
  "TemplateVersions": {},
  "VolatileProperties": {
    "AnalysisLoadTime": 1.197137,
    "ControlCount": {
      "2924002d10ef4e43b50b5d656ee3735f": 1,
      "3e5effa7fd394095b1a41fcfb3450efc": 5,
      "49202fb1a47e43bab329824e5acc0c3a": 5,
      "55e5d1e89528422287eaec6afd3fecd3": 4,
      "aca5d404483a445aab9ac635139797ea": 13,
      "button": 25,
      "circle": 1,
      "dataCard": 23,
      "dropdown": 3,
      "fluidGrid": 11,
      "gallery": 4,
      "galleryTemplate": 4,
      "groupContainer": 10,
      "icon": 23,
      "image": 23,
      "label": 51,
      "powerbi": 6,
      "rectangle": 11,
      "screen": 22
    },
    "DeserializationLoadTime": 4.1550291,
    "ErrorCount": 28
  }
}